AUTHORS
CHANGES
LICENSE
MANIFEST.in
README.rst
setup.py
cked/__init__.py
cked/conf.py
cked/default_settings.py
cked/elFinder.py
cked/fields.py
cked/models.py
cked/urls.py
cked/views.py
cked/widgets.py
cked/static/cked/ckeditor/CHANGES.md
cked/static/cked/ckeditor/LICENSE.md
cked/static/cked/ckeditor/README.md
cked/static/cked/ckeditor/build-config.js
cked/static/cked/ckeditor/ckeditor.js
cked/static/cked/ckeditor/config.js
cked/static/cked/ckeditor/contents.css
cked/static/cked/ckeditor/styles.js
cked/static/cked/ckeditor/lang/af.js
cked/static/cked/ckeditor/lang/ar.js
cked/static/cked/ckeditor/lang/bg.js
cked/static/cked/ckeditor/lang/bn.js
cked/static/cked/ckeditor/lang/bs.js
cked/static/cked/ckeditor/lang/ca.js
cked/static/cked/ckeditor/lang/cs.js
cked/static/cked/ckeditor/lang/cy.js
cked/static/cked/ckeditor/lang/da.js
cked/static/cked/ckeditor/lang/de.js
cked/static/cked/ckeditor/lang/el.js
cked/static/cked/ckeditor/lang/en-au.js
cked/static/cked/ckeditor/lang/en-ca.js
cked/static/cked/ckeditor/lang/en-gb.js
cked/static/cked/ckeditor/lang/en.js
cked/static/cked/ckeditor/lang/eo.js
cked/static/cked/ckeditor/lang/es.js
cked/static/cked/ckeditor/lang/et.js
cked/static/cked/ckeditor/lang/eu.js
cked/static/cked/ckeditor/lang/fa.js
cked/static/cked/ckeditor/lang/fi.js
cked/static/cked/ckeditor/lang/fo.js
cked/static/cked/ckeditor/lang/fr-ca.js
cked/static/cked/ckeditor/lang/fr.js
cked/static/cked/ckeditor/lang/gl.js
cked/static/cked/ckeditor/lang/gu.js
cked/static/cked/ckeditor/lang/he.js
cked/static/cked/ckeditor/lang/hi.js
cked/static/cked/ckeditor/lang/hr.js
cked/static/cked/ckeditor/lang/hu.js
cked/static/cked/ckeditor/lang/is.js
cked/static/cked/ckeditor/lang/it.js
cked/static/cked/ckeditor/lang/ja.js
cked/static/cked/ckeditor/lang/ka.js
cked/static/cked/ckeditor/lang/km.js
cked/static/cked/ckeditor/lang/ko.js
cked/static/cked/ckeditor/lang/ku.js
cked/static/cked/ckeditor/lang/lt.js
cked/static/cked/ckeditor/lang/lv.js
cked/static/cked/ckeditor/lang/mk.js
twentytab_cked.egg-info/PKG-INFO
twentytab_cked.egg-info/SOURCES.txt
twentytab_cked.egg-info/dependency_links.txt
twentytab_cked.egg-info/requires.txt
twentytab_cked.egg-info/top_level.txt