Metadata-Version: 1.0
Name: twentytab-cked
Version: 0.1
Summary: CKEditor and elFinder integration for Django Framework.
Home-page: https://github.com/20tab/twentytab-cked
Author: 20tab srl
Author-email: info@20tab.com
License: BSD
Keywords: django,ckeditor,elfinder,wysiwyg,upload
Platform: UNKNOWN
